kedro_pack/__init__.py
kedro_pack-0.18.12.1.dist-info/LICENSE
kedro_pack-0.18.12.1.dist-info/METADATA
kedro_pack-0.18.12.1.dist-info/WHEEL
kedro_pack-0.18.12.1.dist-info/RECORD
